[
  {
    "ContainingType": "FA.JustBlog.Api.Controllers.Admin.AdminCategoryController",
    "Method": "updateCategory",
    "RelativePath": "api/AdminCategory",
    "HttpMethod": "PUT",
    "IsController": true,
    "Order": 0,
    "Parameters": [
      {
        "Name": "updateCategoryDto",
        "Type": "Application.Dto.CategoryDtos.UpdateCategoryDto",
        "IsRequired": true
      }
    ],
    "ReturnTypes": []
  },
  {
    "ContainingType": "FA.JustBlog.Api.Controllers.Admin.AdminCategoryController",
    "Method": "AddCategory",
    "RelativePath": "api/AdminCategory",
    "HttpMethod": "POST",
    "IsController": true,
    "Order": 0,
    "Parameters": [
      {
        "Name": "createCategoryDto",
        "Type": "Application.Dto.CategoryDtos.CreateCategoryDto",
        "IsRequired": true
      }
    ],
    "ReturnTypes": []
  },
  {
    "ContainingType": "FA.JustBlog.Api.Controllers.Admin.AdminCategoryController",
    "Method": "getCategoryForUpdate",
    "RelativePath": "api/AdminCategory/{id}",
    "HttpMethod": "GET",
    "IsController": true,
    "Order": 0,
    "Parameters": [
      {
        "Name": "id",
        "Type": "System.Int32",
        "IsRequired": true
      }
    ],
    "ReturnTypes": []
  },
  {
    "ContainingType": "FA.JustBlog.Api.Controllers.Admin.AdminCategoryController",
    "Method": "DeleteCategory",
    "RelativePath": "api/AdminCategory/{id}",
    "HttpMethod": "DELETE",
    "IsController": true,
    "Order": 0,
    "Parameters": [
      {
        "Name": "id",
        "Type": "System.Int32",
        "IsRequired": true
      }
    ],
    "ReturnTypes": []
  },
  {
    "ContainingType": "FA.JustBlog.Api.Controllers.Admin.AdminPostController",
    "Method": "GetAll",
    "RelativePath": "api/AdminPost",
    "HttpMethod": "GET",
    "IsController": true,
    "Order": 0,
    "Parameters": [],
    "ReturnTypes": []
  },
  {
    "ContainingType": "FA.JustBlog.Api.Controllers.Admin.AdminPostController",
    "Method": "updateCategory",
    "RelativePath": "api/AdminPost",
    "HttpMethod": "PUT",
    "IsController": true,
    "Order": 0,
    "Parameters": [
      {
        "Name": "updatePostDto",
        "Type": "Application.Dto.PostDtos.UpdatePostDto",
        "IsRequired": true
      }
    ],
    "ReturnTypes": []
  },
  {
    "ContainingType": "FA.JustBlog.Api.Controllers.Admin.AdminPostController",
    "Method": "AddPost",
    "RelativePath": "api/AdminPost",
    "HttpMethod": "POST",
    "IsController": true,
    "Order": 0,
    "Parameters": [
      {
        "Name": "createPostDto",
        "Type": "Application.Dto.PostDtos.CreatePostDto",
        "IsRequired": true
      }
    ],
    "ReturnTypes": []
  },
  {
    "ContainingType": "FA.JustBlog.Api.Controllers.Admin.AdminPostController",
    "Method": "getPostForUpdate",
    "RelativePath": "api/AdminPost/{id}",
    "HttpMethod": "GET",
    "IsController": true,
    "Order": 0,
    "Parameters": [
      {
        "Name": "id",
        "Type": "System.Int32",
        "IsRequired": true
      }
    ],
    "ReturnTypes": []
  },
  {
    "ContainingType": "FA.JustBlog.Api.Controllers.Admin.AdminPostController",
    "Method": "DeletePost",
    "RelativePath": "api/AdminPost/{id}",
    "HttpMethod": "DELETE",
    "IsController": true,
    "Order": 0,
    "Parameters": [
      {
        "Name": "id",
        "Type": "System.Int32",
        "IsRequired": true
      }
    ],
    "ReturnTypes": []
  },
  {
    "ContainingType": "FA.JustBlog.Api.Controllers.Admin.AdminPostController",
    "Method": "PublishPost",
    "RelativePath": "api/AdminPost/PublishPost/{id}",
    "HttpMethod": "PUT",
    "IsController": true,
    "Order": 0,
    "Parameters": [
      {
        "Name": "id",
        "Type": "System.Int32",
        "IsRequired": true
      }
    ],
    "ReturnTypes": []
  },
  {
    "ContainingType": "FA.JustBlog.Api.Controllers.AuthController",
    "Method": "Login",
    "RelativePath": "api/Auth/login",
    "HttpMethod": "POST",
    "IsController": true,
    "Order": 0,
    "Parameters": [
      {
        "Name": "loginDto",
        "Type": "Application.Dto.UserDtos.LoginDto",
        "IsRequired": true
      }
    ],
    "ReturnTypes": []
  },
  {
    "ContainingType": "FA.JustBlog.Api.Controllers.CategoryController",
    "Method": "GetAll",
    "RelativePath": "api/Category",
    "HttpMethod": "GET",
    "IsController": true,
    "Order": 0,
    "Parameters": [],
    "ReturnTypes": []
  },
  {
    "ContainingType": "FA.JustBlog.Api.Controllers.CommentController",
    "Method": "CreateComment",
    "RelativePath": "api/Comment",
    "HttpMethod": "POST",
    "IsController": true,
    "Order": 0,
    "Parameters": [
      {
        "Name": "createCommentDto",
        "Type": "Application.Dto.CommentDtos.CreateCommentDto",
        "IsRequired": true
      }
    ],
    "ReturnTypes": []
  },
  {
    "ContainingType": "FA.JustBlog.Api.Controllers.CommentController",
    "Method": "DeleteComment",
    "RelativePath": "api/Comment/{commentId}",
    "HttpMethod": "DELETE",
    "IsController": true,
    "Order": 0,
    "Parameters": [
      {
        "Name": "commentId",
        "Type": "System.Int32",
        "IsRequired": true
      }
    ],
    "ReturnTypes": []
  },
  {
    "ContainingType": "FA.JustBlog.Api.Controllers.PostController",
    "Method": "GetAllForUser",
    "RelativePath": "api/Post",
    "HttpMethod": "GET",
    "IsController": true,
    "Order": 0,
    "Parameters": [],
    "ReturnTypes": []
  },
  {
    "ContainingType": "FA.JustBlog.Api.Controllers.PostController",
    "Method": "GetPostById",
    "RelativePath": "api/Post/{id}",
    "HttpMethod": "GET",
    "IsController": true,
    "Order": 0,
    "Parameters": [
      {
        "Name": "id",
        "Type": "System.Int32",
        "IsRequired": true
      }
    ],
    "ReturnTypes": []
  },
  {
    "ContainingType": "FA.JustBlog.Api.Controllers.PostController",
    "Method": "FindPostx",
    "RelativePath": "api/Post/{year}/{month}/{title}",
    "HttpMethod": "GET",
    "IsController": true,
    "Order": 0,
    "Parameters": [
      {
        "Name": "year",
        "Type": "System.Int32",
        "IsRequired": true
      },
      {
        "Name": "month",
        "Type": "System.Int32",
        "IsRequired": true
      },
      {
        "Name": "title",
        "Type": "System.String",
        "IsRequired": true
      }
    ],
    "ReturnTypes": []
  },
  {
    "ContainingType": "FA.JustBlog.Api.Controllers.PostController",
    "Method": "GetPostByCategory",
    "RelativePath": "api/Post/category/{id}",
    "HttpMethod": "GET",
    "IsController": true,
    "Order": 0,
    "Parameters": [
      {
        "Name": "id",
        "Type": "System.Int32",
        "IsRequired": true
      }
    ],
    "ReturnTypes": []
  },
  {
    "ContainingType": "FA.JustBlog.Api.Controllers.PostController",
    "Method": "GetPostByFilter",
    "RelativePath": "api/Post/filter/{index}",
    "HttpMethod": "GET",
    "IsController": true,
    "Order": 0,
    "Parameters": [
      {
        "Name": "sapxep",
        "Type": "System.String",
        "IsRequired": false
      },
      {
        "Name": "ispublish",
        "Type": "System.String",
        "IsRequired": false
      },
      {
        "Name": "index",
        "Type": "System.Int32",
        "IsRequired": true
      },
      {
        "Name": "pageSize",
        "Type": "System.Int32",
        "IsRequired": false
      }
    ],
    "ReturnTypes": []
  },
  {
    "ContainingType": "FA.JustBlog.Api.Controllers.PostController",
    "Method": "GetMyPost",
    "RelativePath": "api/Post/mypost",
    "HttpMethod": "GET",
    "IsController": true,
    "Order": 0,
    "Parameters": [],
    "ReturnTypes": []
  },
  {
    "ContainingType": "FA.JustBlog.Api.Controllers.PostController",
    "Method": "GetPostPage",
    "RelativePath": "api/Post/page/{index}",
    "HttpMethod": "GET",
    "IsController": true,
    "Order": 0,
    "Parameters": [
      {
        "Name": "index",
        "Type": "System.Int32",
        "IsRequired": true
      },
      {
        "Name": "pageSize",
        "Type": "System.Int32",
        "IsRequired": false
      }
    ],
    "ReturnTypes": []
  },
  {
    "ContainingType": "FA.JustBlog.Api.Controllers.PostController",
    "Method": "GetPostByTag",
    "RelativePath": "api/Post/tag/{tagName}",
    "HttpMethod": "GET",
    "IsController": true,
    "Order": 0,
    "Parameters": [
      {
        "Name": "tagName",
        "Type": "System.String",
        "IsRequired": true
      }
    ],
    "ReturnTypes": []
  },
  {
    "ContainingType": "FA.JustBlog.Api.Controllers.PostController",
    "Method": "GetTopView",
    "RelativePath": "api/Post/topview/{top}",
    "HttpMethod": "GET",
    "IsController": true,
    "Order": 0,
    "Parameters": [
      {
        "Name": "top",
        "Type": "System.Int32",
        "IsRequired": true
      }
    ],
    "ReturnTypes": []
  },
  {
    "ContainingType": "FA.JustBlog.Api.Controllers.PostRateController",
    "Method": "RatePost",
    "RelativePath": "api/PostRate/rate/{postId}",
    "HttpMethod": "PUT",
    "IsController": true,
    "Order": 0,
    "Parameters": [
      {
        "Name": "postId",
        "Type": "System.Int32",
        "IsRequired": true
      },
      {
        "Name": "point",
        "Type": "System.Decimal",
        "IsRequired": false
      }
    ],
    "ReturnTypes": []
  },
  {
    "ContainingType": "FA.JustBlog.Api.Controllers.TagController",
    "Method": "GetTopPopular",
    "RelativePath": "api/Tag/toppopular/{top}",
    "HttpMethod": "GET",
    "IsController": true,
    "Order": 0,
    "Parameters": [
      {
        "Name": "top",
        "Type": "System.Int32",
        "IsRequired": true
      }
    ],
    "ReturnTypes": []
  },
  {
    "ContainingType": "FA.JustBlog.Api.Controllers.UserController",
    "Method": "Get",
    "RelativePath": "api/User/{id}",
    "HttpMethod": "GET",
    "IsController": true,
    "Order": 0,
    "Parameters": [
      {
        "Name": "id",
        "Type": "System.Int32",
        "IsRequired": true
      }
    ],
    "ReturnTypes": []
  }
]